fiduswriter/phplist/__init__.py
fiduswriter/phplist/apps.py
fiduswriter/phplist/urls.py
fiduswriter/phplist/views.py
fiduswriter/phplist/locale/BASE/LC_MESSAGES/djangojs.po
fiduswriter/phplist/locale/bg/LC_MESSAGES/djangojs.mo
fiduswriter/phplist/locale/bg/LC_MESSAGES/djangojs.po
fiduswriter/phplist/locale/de/LC_MESSAGES/djangojs.mo
fiduswriter/phplist/locale/de/LC_MESSAGES/djangojs.po
fiduswriter/phplist/locale/es/LC_MESSAGES/djangojs.mo
fiduswriter/phplist/locale/es/LC_MESSAGES/djangojs.po
fiduswriter/phplist/locale/fr/LC_MESSAGES/djangojs.mo
fiduswriter/phplist/locale/fr/LC_MESSAGES/djangojs.po
fiduswriter/phplist/locale/it/LC_MESSAGES/djangojs.mo
fiduswriter/phplist/locale/it/LC_MESSAGES/djangojs.po
fiduswriter/phplist/locale/pt_BR/LC_MESSAGES/djangojs.mo
fiduswriter/phplist/locale/pt_BR/LC_MESSAGES/djangojs.po
fiduswriter/phplist/static/js/modules/phplist/index.js
fiduswriter/phplist/static/js/modules/phplist/templates.js
fiduswriter/phplist/static/js/plugins/confirm_account/phplist.js
fiduswriter/phplist/tests/__init__.py
fiduswriter/phplist/tests/test_phplist.py
fiduswriter_phplist-4.0.0.dist-info/licenses/LICENSE
fiduswriter_phplist-4.0.0.dist-info/METADATA
fiduswriter_phplist-4.0.0.dist-info/WHEEL
fiduswriter_phplist-4.0.0.dist-info/top_level.txt
fiduswriter_phplist-4.0.0.dist-info/RECORD
